Metadata-Version: 2.2
Name: pymeshoptimizer
Version: 0.3.0
Summary: High-level abstractions and utilities for working with meshoptimizer
Home-page: https://github.com/username/pymeshoptimizer
Classifier: Programming Language :: Python :: 3
Classifier: Programming Language :: Python :: 3.8
Classifier: Programming Language :: Python :: 3.9
Classifier: Programming Language :: Python :: 3.10
Classifier: Programming Language :: Python :: 3.11
Classifier: License :: OSI Approved :: MIT License
Classifier: Operating System :: OS Independent
Classifier: Topic :: Scientific/Engineering :: Mathematics
Classifier: Topic :: Multimedia :: Graphics :: 3D Modeling
Classifier: Intended Audience :: Developers
Classifier: Intended Audience :: Science/Research
Requires-Python: >=3.8
Requires-Dist: numpy>=1.19.0
Requires-Dist: meshoptimizer==0.2.20a4
Requires-Dist: pydantic>=2.0.0
Dynamic: classifier
Dynamic: description
Dynamic: description-content-type
Dynamic: home-page
Dynamic: requires-dist
Dynamic: requires-python
Dynamic: summary
